dpod/__init__.py
dpod/config.py
dpod/archtool_conf/__init__.py
dpod/archtool_conf/bundle_project.py
dpod/archtool_conf/custom_layers.py
dpod/core/__init__.py
dpod/core/controllers.py
dpod/core/deps.py
dpod/core/dtos.py
dpod/core/interfaces.py
dpod/core/repos.py
dpod/core/services.py
dpod/entrypoints/__init__.py
dpod/entrypoints/commander.py
dpod-0.1.13.dist-info/METADATA
dpod-0.1.13.dist-info/WHEEL
dpod-0.1.13.dist-info/entry_points.txt
dpod-0.1.13.dist-info/top_level.txt
dpod-0.1.13.dist-info/RECORD
