Metadata-Version: 2.4
Name: dpod
Version: 0.1.13
Summary: CLI для взаимодействия с Dispersion Platform
Requires-Python: >=3.12
Requires-Dist: httpx
Requires-Dist: questionary
Requires-Dist: rich
Requires-Dist: click
Requires-Dist: uv
Requires-Dist: archtool
Requires-Dist: web_fractal
Requires-Dist: fastapi
Requires-Dist: sqlalchemy
Requires-Dist: aiohttp
Requires-Dist: furl
Requires-Dist: docker
Requires-Dist: harborapi
Requires-Dist: zmq
Requires-Dist: pytz
